pychemengg/__init__.py
pychemengg/heattransfer/__init__.py
pychemengg/heattransfer/externalflow.py
pychemengg/heattransfer/fins.py
pychemengg/heattransfer/heatcommonmethods.py
pychemengg/heattransfer/heatexchangers.py
pychemengg/heattransfer/internalflow.py
pychemengg/heattransfer/steadystate.py
pychemengg/heattransfer/transient.py
pychemengg/massbalances/__init__.py
pychemengg/massbalances/physicalmassbalance.py
pychemengg/physicalproperties/__init__.py
pychemengg/physicalproperties/airproperties.py
pychemengg/physicalproperties/data_airproperties.txt
pychemengg/physicalproperties/data_waterproperties.txt
pychemengg/physicalproperties/waterliquidproperties.py
pychemengg/physicalproperties/watervaporproperties.py
pychemengg-0.1a11.dist-info/License.txt
pychemengg-0.1a11.dist-info/METADATA
pychemengg-0.1a11.dist-info/WHEEL
pychemengg-0.1a11.dist-info/top_level.txt
pychemengg-0.1a11.dist-info/RECORD
