Metadata-Version: 2.1
Name: pychemengg
Version: 0.1a11
Summary: A framework for problem solving and critical thinking in chemical engineering.
Home-page: https://github.com/profhsgill
Author: Prof. Harvinder Singh Gill
Author-email: profhsgill@gmail.com
License: UNKNOWN
Keywords: chemical engineering,chemical-engineering,heat transfer,heat-transfer,material balances,material-balances,chemical reaction engineering,thermodynamics,reactions,reactors,reaction-engineering,process control,fluid flow
Platform: UNKNOWN
Classifier: Programming Language :: Python :: 3
Classifier: License :: OSI Approved :: MIT License
Classifier: Development Status :: 3 - Alpha
Classifier: Environment :: Console
Classifier: Environment :: Web Environment
Classifier: Intended Audience :: Education
Classifier: Intended Audience :: End Users/Desktop
Classifier: Natural Language :: English
Classifier: Operating System :: OS Independent
Classifier: Topic :: Education
Classifier: Topic :: Scientific/Engineering
Requires-Python: >=3
License-File: License.txt
Requires-Dist: numpy
Requires-Dist: scipy
